phys2denoise/__init__.py
phys2denoise/_version.py
phys2denoise/due.py
phys2denoise/references.py
phys2denoise/workflow.py
phys2denoise/cli/__init__.py
phys2denoise/cli/run.py
phys2denoise/metrics/__init__.py
phys2denoise/metrics/cardiac.py
phys2denoise/metrics/chest_belt.py
phys2denoise/metrics/gas.py
phys2denoise/metrics/multimodal.py
phys2denoise/metrics/responses.py
phys2denoise/metrics/utils.py
phys2denoise/tests/__init__.py
phys2denoise/tests/conftest.py
phys2denoise/tests/test_metrics_cardiac.py
phys2denoise/tests/test_metrics_chest_belt.py
phys2denoise/tests/test_metrics_utils.py
phys2denoise/tests/test_rvt.py
phys2denoise-0.5.0.dist-info/LICENSE
phys2denoise-0.5.0.dist-info/METADATA
phys2denoise-0.5.0.dist-info/WHEEL
phys2denoise-0.5.0.dist-info/entry_points.txt
phys2denoise-0.5.0.dist-info/top_level.txt
phys2denoise-0.5.0.dist-info/RECORD
