Metadata-Version: 2.1
Name: phys2denoise
Version: 0.5.0
Summary: A collection of scripts to prepare physiological data for fMRI denoising
Home-page: https://github.com/physiopy/phys2denoise
Download-URL: https://github.com/physiopy/phys2denoise
Author: The Physiopy Community
Maintainer: The Physiopy Community
Maintainer-email: physiopy.community@gmail.com
License: Apache-2.0
Platform: OS Independent
Classifier: Development Status :: 3 - Alpha
Classifier: Intended Audience :: Science/Research
Classifier: License :: OSI Approved :: Apache Software License
Classifier: Programming Language :: Python :: 3
Provides: phys2denoise
Requires-Python: >=3.9
License-File: LICENSE
Requires-Dist: numpy<2,>=1.9.3
Requires-Dist: matplotlib
Requires-Dist: pandas
Requires-Dist: scipy
Requires-Dist: duecredit
Requires-Dist: loguru
Requires-Dist: physutils>=0.2.1
Provides-Extra: dev
Requires-Dist: pre-commit; extra == "dev"
Requires-Dist: sphinx>=2.0; extra == "dev"
Requires-Dist: sphinx-argparse; extra == "dev"
Requires-Dist: sphinx-rtd-theme; extra == "dev"
Requires-Dist: myst-parser; extra == "dev"
Requires-Dist: flake8>=4.0; extra == "dev"
Requires-Dist: black; extra == "dev"
Requires-Dist: isort<6.0.0; extra == "dev"
Requires-Dist: pydocstyle; extra == "dev"
Requires-Dist: pytest>=5.3; extra == "dev"
Requires-Dist: pytest-cov; extra == "dev"
Requires-Dist: peakdet>=0.5.0; extra == "dev"
Requires-Dist: coverage; extra == "dev"
Provides-Extra: devtools
Requires-Dist: pre-commit; extra == "devtools"
Provides-Extra: doc
Requires-Dist: sphinx>=2.0; extra == "doc"
Requires-Dist: sphinx-argparse; extra == "doc"
Requires-Dist: sphinx-rtd-theme; extra == "doc"
Requires-Dist: myst-parser; extra == "doc"
Provides-Extra: style
Requires-Dist: flake8>=4.0; extra == "style"
Requires-Dist: black; extra == "style"
Requires-Dist: isort<6.0.0; extra == "style"
Requires-Dist: pydocstyle; extra == "style"
Provides-Extra: test
Requires-Dist: flake8>=4.0; extra == "test"
Requires-Dist: black; extra == "test"
Requires-Dist: isort<6.0.0; extra == "test"
Requires-Dist: pydocstyle; extra == "test"
Requires-Dist: pytest>=5.3; extra == "test"
Requires-Dist: pytest-cov; extra == "test"
Requires-Dist: peakdet>=0.5.0; extra == "test"
Requires-Dist: coverage; extra == "test"
